sphinx_d2/__about__.py
sphinx_d2/__init__.py
sphinx_d2/main.py
sphinx_d2-0.0.1.dist-info/METADATA
sphinx_d2-0.0.1.dist-info/WHEEL
sphinx_d2-0.0.1.dist-info/licenses/LICENSE.txt
sphinx_d2-0.0.1.dist-info/RECORD
